puggle/__init__.py
puggle/Annotation.py
puggle/data_utils/__init__.py
puggle/data_utils/manipulation.py
puggle/data_utils/sampling.py
puggle/data_utils/statistics.py
puggle/Dataset.py
puggle/Document.py
puggle/logger.py
puggle/Mention.py
puggle/Relation.py
puggle/size_limits.py
puggle/utils.py
puggle-0.2.13.dist-info/METADATA
puggle-0.2.13.dist-info/WHEEL
puggle-0.2.13.dist-info/RECORD
