Metadata-Version: 2.1
Name: puggle
Version: 0.2.13
Summary: 
Author: Michael Stewart
Author-email: michael.stewart.webdev@gmail.com
Requires-Python: >=3.10,<4.0
Classifier: Programming Language :: Python :: 3
Classifier: Programming Language :: Python :: 3.10
Classifier: Programming Language :: Python :: 3.11
Requires-Dist: colorama (>=0.4.6,<0.5.0)
Requires-Dist: loguru (>=0.7.2,<0.8.0)
Requires-Dist: py2neo (>=2021.2.4,<2022.0.0)
Requires-Dist: python-dotenv (>=1.0.0,<2.0.0)
